poly_hammer_utils/__init__.py
poly_hammer_utils/addon/packager.py
poly_hammer_utils/addon/release.py
poly_hammer_utils/constants.py
poly_hammer_utils/extension/meta_human_dna.py
poly_hammer_utils/extension/packager.py
poly_hammer_utils/extension/server.py
poly_hammer_utils/github/release.py
poly_hammer_utils/helpers.py
poly_hammer_utils/launch.py
poly_hammer_utils/resources/scripts/blender/startup.py
poly_hammer_utils/resources/scripts/unreal/init_unreal.py
poly_hammer_utils/utilities.py
poly_hammer_utils-0.0.27.dist-info/METADATA
poly_hammer_utils-0.0.27.dist-info/WHEEL
poly_hammer_utils-0.0.27.dist-info/RECORD
