Metadata-Version: 2.1
Name: poly-hammer-utils
Version: 0.0.27
Summary: 
Author: Poly Hammer
Author-email: info@polyhammer.com
Requires-Python: >=3.11,<4.0
Classifier: Programming Language :: Python :: 3
Classifier: Programming Language :: Python :: 3.11
Classifier: Programming Language :: Python :: 3.12
Requires-Dist: PyGithub (==2.5.0)
Requires-Dist: boto3 (>=1.42.35,<2.0.0)
Requires-Dist: httpx (>=0.28.1,<0.29.0)
Requires-Dist: python-dotenv (>=1.1.1,<2.0.0)
Requires-Dist: requirements-parser (>=0.11.0,<0.12.0)
Requires-Dist: tomlkit (>=0.14.0,<0.15.0)
